pyunique/__init__.py
pyunique/archive.py
pyunique/configs.py
pyunique/digest.py
pyunique/main.py
pyunique/static.py
pyunique/utils.py
pyunique-0.0.11.dist-info/LICENSE
pyunique-0.0.11.dist-info/METADATA
pyunique-0.0.11.dist-info/WHEEL
pyunique-0.0.11.dist-info/entry_points.txt
pyunique-0.0.11.dist-info/top_level.txt
pyunique-0.0.11.dist-info/RECORD
